ReprTraceback/ReprTraceback.py
ReprTraceback/__init__.py
ReprTraceback-1.0.4.dist-info/METADATA
ReprTraceback-1.0.4.dist-info/WHEEL
ReprTraceback-1.0.4.dist-info/top_level.txt
ReprTraceback-1.0.4.dist-info/RECORD
