Metadata-Version: 2.1
Name: ReprTraceback
Version: 1.0.4
Summary: Improve stack traces with the values associated with each argument in each frame.
Home-page: https://github.com/NateRiz/ReprTraceback
Author: NateRiz
Author-email: natezriz@gmail.com
Classifier: Programming Language :: Python :: 3
Classifier: Programming Language :: Python :: 3.11
